[
    {
        "x0": 38.88,
        "y0": 761.48,
        "x1": 571.6800000000001,
        "y1": 761.48,
        "width": 532.8000000000001,
        "height": 0,
        "pts": [
            [
                38.88,
                30.720000000000027
            ],
            [
                39.36,
                30.720000000000027
            ],
            [
                39.36,
                30.24000000000001
            ],
            [
                38.88,
                30.24000000000001
            ]
        ],
        "linewidth": 0,
        "stroke": false,
        "fill": true,
        "evenodd": false,
        "stroking_color": null,
        "non_stroking_color": [
            0
        ],
        "mcid": 3,
        "tag": "Artifact",
        "object_type": "rect_edge",
        "page_number": 1,
        "stroking_pattern": null,
        "non_stroking_pattern": null,
        "top": 30.52000000000002,
        "bottom": 30.52000000000002,
        "doctop": 30.52000000000002,
        "orientation": "h"
    },
    {
        "x0": 38.88,
        "y0": 746.6241333333332,
        "x1": 571.6800000000001,
        "y1": 746.6241333333332,
        "width": 532.8000000000001,
        "height": 0,
        "pts": [
            [
                38.88,
                45.120000000000005
            ],
            [
                39.36,
                45.120000000000005
            ],
            [
                39.36,
                30.720000000000027
            ],
            [
                38.88,
                30.720000000000027
            ]
        ],
        "linewidth": 0,
        "stroke": false,
        "fill": true,
        "evenodd": false,
        "stroking_color": null,
        "non_stroking_color": [
            0
        ],
        "mcid": 3,
        "tag": "Artifact",
        "object_type": "rect_edge",
        "page_number": 1,
        "stroking_pattern": null,
        "non_stroking_pattern": null,
        "top": 45.37586666666671,
        "bottom": 45.37586666666671,
        "doctop": 45.37586666666671,
        "orientation": "h"
    },
    {
        "x0": 38.88,
        "y0": 709.5603125,
        "x1": 571.6800000000001,
        "y1": 709.5603125,
        "width": 532.8000000000001,
        "height": 0,
        "pts": [
            [
                38.88,
                82.20000000000005
            ],
            [
                39.36,
                82.20000000000005
            ],
            [
                39.36,
                45.601
            ],
            [
                38.88,
                45.601
            ]
        ],
        "linewidth": 0,
        "stroke": false,
        "fill": true,
        "evenodd": false,
        "stroking_color": null,
        "non_stroking_color": [
            0
        ],
        "mcid": 20,
        "tag": "Artifact",
        "object_type": "rect_edge",
        "page_number": 1,
        "stroking_pattern": null,
        "non_stroking_pattern": null,
        "top": 82.43968750000003,
        "bottom": 82.43968750000003,
        "doctop": 82.43968750000003,
        "orientation": "h"
    },
    {
        "x0": 38.88,
        "y0": 660.8560000000001,
        "x1": 571.6800000000001,
        "y1": 660.8560000000001,
        "width": 532.8000000000001,
        "height": 0,
        "pts": [
            [
                38.88,
                130.91999999999996
            ],
            [
                39.36,
                130.91999999999996
            ],
            [
                39.36,
                82.67999999999995
            ],
            [
                38.88,
                82.67999999999995
            ]
        ],
        "linewidth": 0,
        "stroke": false,
        "fill": true,
        "evenodd": false,
        "stroking_color": null,
        "non_stroking_color": [
            0
        ],
        "mcid": 37,
        "tag": "Artifact",
        "object_type": "rect_edge",
        "page_number": 1,
        "stroking_pattern": null,
        "non_stroking_pattern": null,
        "top": 131.14399999999992,
        "bottom": 131.14399999999992,
        "doctop": 131.14399999999992,
        "orientation": "h"
    },
    {
        "x0": 38.88,
        "y0": 646.0800000000002,
        "x1": 571.6800000000001,
        "y1": 646.0800000000002,
        "width": 532.8000000000001,
        "height": 0,
        "pts": [
            [
                38.88,
                145.67999999999995
            ],
            [
                39.36,
                145.67999999999995
            ],
            [
                39.36,
                131.39999999999998
            ],
            [
                38.88,
                131.39999999999998
            ]
        ],
        "linewidth": 0,
        "stroke": false,
        "fill": true,
        "evenodd": false,
        "stroking_color": null,
        "non_stroking_color": [
            0
        ],
        "mcid": 41,
        "tag": "Artifact",
        "object_type": "rect_edge",
        "page_number": 1,
        "stroking_pattern": null,
        "non_stroking_pattern": null,
        "top": 145.9199999999999,
        "bottom": 145.9199999999999,
        "doctop": 145.9199999999999,
        "orientation": "h"
    },
    {
        "x0": 38.88,
        "y0": 622.24,
        "x1": 571.6800000000001,
        "y1": 622.24,
        "width": 532.8000000000001,
        "height": 0,
        "pts": [
            [
                38.88,
                169.55999999999995
            ],
            [
                39.36,
                169.55999999999995
            ],
            [
                39.36,
                146.15999999999997
            ],
            [
                38.88,
                146.15999999999997
            ]
        ],
        "linewidth": 0,
        "stroke": false,
        "fill": true,
        "evenodd": false,
        "stroking_color": null,
        "non_stroking_color": [
            0
        ],
        "mcid": 45,
        "tag": "Artifact",
        "object_type": "rect_edge",
        "page_number": 1,
        "stroking_pattern": null,
        "non_stroking_pattern": null,
        "top": 169.75999999999993,
        "bottom": 169.75999999999993,
        "doctop": 169.75999999999993,
        "orientation": "h"
    },
    {
        "x0": 37.44,
        "y0": 614.64,
        "x1": 299.52,
        "y1": 614.64,
        "width": 262.08,
        "height": 0,
        "pts": [
            [
                37.44,
                177.60000000000002
            ],
            [
                299.52,
                177.60000000000002
            ],
            [
                299.52,
                177.12
            ],
            [
                37.44,
                177.12
            ]
        ],
        "linewidth": 0,
        "stroke": false,
        "fill": true,
        "evenodd": false,
        "stroking_color": null,
        "non_stroking_color": [
            0
        ],
        "mcid": 47,
        "tag": "P",
        "object_type": "rect_edge",
        "page_number": 1,
        "stroking_pattern": null,
        "non_stroking_pattern": null,
        "top": 177.36,
        "bottom": 177.36,
        "doctop": 177.36,
        "orientation": "h"
    },
    {
        "x0": 37.44,
        "y0": 595.5600000000001,
        "x1": 299.52,
        "y1": 595.5600000000001,
        "width": 262.08,
        "height": 0,
        "pts": [
            [
                37.44,
                196.67999999999995
            ],
            [
                299.52,
                196.67999999999995
            ],
            [
                299.52,
                196.19999999999993
            ],
            [
                37.44,
                196.19999999999993
            ]
        ],
        "linewidth": 0,
        "stroke": false,
        "fill": true,
        "evenodd": false,
        "stroking_color": null,
        "non_stroking_color": [
            0
        ],
        "mcid": 47,
        "tag": "P",
        "object_type": "rect_edge",
        "page_number": 1,
        "stroking_pattern": null,
        "non_stroking_pattern": null,
        "top": 196.43999999999994,
        "bottom": 196.43999999999994,
        "doctop": 196.43999999999994,
        "orientation": "h"
    },
    {
        "x0": 311.04,
        "y0": 462.12000000000006,
        "x1": 573.12,
        "y1": 462.12000000000006,
        "width": 262.08,
        "height": 0,
        "pts": [
            [
                311.04,
                330.12
            ],
            [
                573.12,
                330.12
            ],
            [
                573.12,
                329.64
            ],
            [
                311.04,
                329.64
            ]
        ],
        "linewidth": 0,
        "stroke": false,
        "fill": true,
        "evenodd": false,
        "stroking_color": null,
        "non_stroking_color": [
            0
        ],
        "mcid": 91,
        "tag": "P",
        "object_type": "rect_edge",
        "page_number": 1,
        "stroking_pattern": null,
        "non_stroking_pattern": null,
        "top": 329.87999999999994,
        "bottom": 329.87999999999994,
        "doctop": 329.87999999999994,
        "orientation": "h"
    },
    {
        "x0": 311.04,
        "y0": 442.91999999999996,
        "x1": 573.12,
        "y1": 442.91999999999996,
        "width": 262.08,
        "height": 0,
        "pts": [
            [
                311.04,
                349.32
            ],
            [
                573.12,
                349.32
            ],
            [
                573.12,
                348.84
            ],
            [
                311.04,
                348.84
            ]
        ],
        "linewidth": 0,
        "stroke": false,
        "fill": true,
        "evenodd": false,
        "stroking_color": null,
        "non_stroking_color": [
            0
        ],
        "mcid": 91,
        "tag": "P",
        "object_type": "rect_edge",
        "page_number": 1,
        "stroking_pattern": null,
        "non_stroking_pattern": null,
        "top": 349.08000000000004,
        "bottom": 349.08000000000004,
        "doctop": 349.08000000000004,
        "orientation": "h"
    },
    {
        "x0": 306.6,
        "y0": 406.99999999999994,
        "x1": 577.5600000000001,
        "y1": 406.99999999999994,
        "width": 270.96000000000004,
        "height": 0,
        "pts": [
            [
                306.6,
                385.2
            ],
            [
                307.08000000000004,
                385.2
            ],
            [
                307.08000000000004,
                384.71999999999997
            ],
            [
                306.6,
                384.71999999999997
            ]
        ],
        "linewidth": 0,
        "stroke": false,
        "fill": true,
        "evenodd": false,
        "stroking_color": null,
        "non_stroking_color": [
            0
        ],
        "mcid": 93,
        "tag": "P",
        "object_type": "rect_edge",
        "page_number": 1,
        "stroking_pattern": null,
        "non_stroking_pattern": null,
        "top": 385.00000000000006,
        "bottom": 385.00000000000006,
        "doctop": 385.00000000000006,
        "orientation": "h"
    },
    {
        "x0": 306.6,
        "y0": 387.9600000000003,
        "x1": 577.5600000000001,
        "y1": 387.9600000000003,
        "width": 270.96000000000004,
        "height": 0,
        "pts": [
            [
                306.6,
                404.28
            ],
            [
                307.08000000000004,
                404.28
            ],
            [
                307.08000000000004,
                403.79999999999995
            ],
            [
                306.6,
                403.79999999999995
            ]
        ],
        "linewidth": 0,
        "stroke": false,
        "fill": true,
        "evenodd": false,
        "stroking_color": null,
        "non_stroking_color": [
            0
        ],
        "mcid": 93,
        "tag": "P",
        "object_type": "rect_edge",
        "page_number": 1,
        "stroking_pattern": null,
        "non_stroking_pattern": null,
        "top": 404.0399999999997,
        "bottom": 404.0399999999997,
        "doctop": 404.0399999999997,
        "orientation": "h"
    },
    {
        "x0": 33.0,
        "y0": 269.52012499999984,
        "x1": 307.08000000000004,
        "y1": 269.52012499999984,
        "width": 274.08000000000004,
        "height": 0,
        "pts": [
            [
                33.0,
                522.8399999999999
            ],
            [
                33.48,
                522.8399999999999
            ],
            [
                33.48,
                522.3599999999999
            ],
            [
                33.0,
                522.3599999999999
            ]
        ],
        "linewidth": 0,
        "stroke": false,
        "fill": true,
        "evenodd": false,
        "stroking_color": null,
        "non_stroking_color": [
            0
        ],
        "mcid": 71,
        "tag": "P",
        "object_type": "rect_edge",
        "page_number": 1,
        "stroking_pattern": null,
        "non_stroking_pattern": null,
        "top": 522.4798750000001,
        "bottom": 522.4798750000001,
        "doctop": 522.4798750000001,
        "orientation": "h"
    },
    {
        "x0": 33.0,
        "y0": 254.6133333333328,
        "x1": 307.08000000000004,
        "y1": 254.6133333333328,
        "width": 274.08000000000004,
        "height": 0,
        "pts": [
            [
                33.0,
                538.08
            ],
            [
                33.48,
                538.08
            ],
            [
                33.48,
                522.8389999999999
            ],
            [
                33.0,
                522.8389999999999
            ]
        ],
        "linewidth": 0,
        "stroke": false,
        "fill": true,
        "evenodd": false,
        "stroking_color": null,
        "non_stroking_color": [
            0
        ],
        "mcid": 71,
        "tag": "P",
        "object_type": "rect_edge",
        "page_number": 1,
        "stroking_pattern": null,
        "non_stroking_pattern": null,
        "top": 537.3866666666671,
        "bottom": 537.3866666666671,
        "doctop": 537.3866666666671,
        "orientation": "h"
    },
    {
        "x0": 303.48,
        "y0": 216.84024999999994,
        "x1": 307.08000000000004,
        "y1": 216.84024999999994,
        "width": 3.6000000000000227,
        "height": 0,
        "pts": [
            [
                303.48,
                575.4
            ],
            [
                303.96000000000004,
                575.4
            ],
            [
                303.96000000000004,
                563.76
            ],
            [
                303.48,
                563.76
            ]
        ],
        "linewidth": 0,
        "stroke": false,
        "fill": true,
        "evenodd": false,
        "stroking_color": null,
        "non_stroking_color": [
            0
        ],
        "mcid": 75,
        "tag": "LBody",
        "object_type": "rect_edge",
        "page_number": 1,
        "stroking_pattern": null,
        "non_stroking_pattern": null,
        "top": 575.15975,
        "bottom": 575.15975,
        "doctop": 575.15975,
        "orientation": "h"
    },
    {
        "x0": 303.48,
        "y0": 205.1397499999998,
        "x1": 307.08000000000004,
        "y1": 205.1397499999998,
        "width": 3.6000000000000227,
        "height": 0,
        "pts": [
            [
                303.48,
                587.04
            ],
            [
                303.96000000000004,
                587.04
            ],
            [
                303.96000000000004,
                575.399
            ],
            [
                303.48,
                575.399
            ]
        ],
        "linewidth": 0,
        "stroke": false,
        "fill": true,
        "evenodd": false,
        "stroking_color": null,
        "non_stroking_color": [
            0
        ],
        "mcid": 75,
        "tag": "LBody",
        "object_type": "rect_edge",
        "page_number": 1,
        "stroking_pattern": null,
        "non_stroking_pattern": null,
        "top": 586.8602500000002,
        "bottom": 586.8602500000002,
        "doctop": 586.8602500000002,
        "orientation": "h"
    },
    {
        "x0": 303.48,
        "y0": 193.13999999999996,
        "x1": 307.08000000000004,
        "y1": 193.13999999999996,
        "width": 3.6000000000000227,
        "height": 0,
        "pts": [
            [
                303.48,
                599.28
            ],
            [
                303.96000000000004,
                599.28
            ],
            [
                303.96000000000004,
                587.04
            ],
            [
                303.48,
                587.04
            ]
        ],
        "linewidth": 0,
        "stroke": false,
        "fill": true,
        "evenodd": false,
        "stroking_color": null,
        "non_stroking_color": [
            0
        ],
        "mcid": 79,
        "tag": "LBody",
        "object_type": "rect_edge",
        "page_number": 1,
        "stroking_pattern": null,
        "non_stroking_pattern": null,
        "top": 598.86,
        "bottom": 598.86,
        "doctop": 598.86,
        "orientation": "h"
    },
    {
        "x0": 303.48,
        "y0": 181.38025000000013,
        "x1": 307.08000000000004,
        "y1": 181.38025000000013,
        "width": 3.6000000000000227,
        "height": 0,
        "pts": [
            [
                303.48,
                610.92
            ],
            [
                303.96000000000004,
                610.92
            ],
            [
                303.96000000000004,
                599.28
            ],
            [
                303.48,
                599.28
            ]
        ],
        "linewidth": 0,
        "stroke": false,
        "fill": true,
        "evenodd": false,
        "stroking_color": null,
        "non_stroking_color": [
            0
        ],
        "mcid": 79,
        "tag": "LBody",
        "object_type": "rect_edge",
        "page_number": 1,
        "stroking_pattern": null,
        "non_stroking_pattern": null,
        "top": 610.6197499999998,
        "bottom": 610.6197499999998,
        "doctop": 610.6197499999998,
        "orientation": "h"
    },
    {
        "x0": 303.48,
        "y0": 169.74000000000052,
        "x1": 307.08000000000004,
        "y1": 169.74000000000052,
        "width": 3.6000000000000227,
        "height": 0,
        "pts": [
            [
                303.48,
                622.56
            ],
            [
                303.96000000000004,
                622.56
            ],
            [
                303.96000000000004,
                610.9200000000001
            ],
            [
                303.48,
                610.9200000000001
            ]
        ],
        "linewidth": 0,
        "stroke": false,
        "fill": true,
        "evenodd": false,
        "stroking_color": null,
        "non_stroking_color": [
            0
        ],
        "mcid": 79,
        "tag": "LBody",
        "object_type": "rect_edge",
        "page_number": 1,
        "stroking_pattern": null,
        "non_stroking_pattern": null,
        "top": 622.2599999999995,
        "bottom": 622.2599999999995,
        "doctop": 622.2599999999995,
        "orientation": "h"
    },
    {
        "x0": 33.0,
        "y0": 156.9903125000004,
        "x1": 307.08000000000004,
        "y1": 156.9903125000004,
        "width": 274.08000000000004,
        "height": 0,
        "pts": [
            [
                33.0,
                635.64
            ],
            [
                33.48,
                635.64
            ],
            [
                33.48,
                635.159
            ],
            [
                33.0,
                635.159
            ]
        ],
        "linewidth": 0,
        "stroke": false,
        "fill": true,
        "evenodd": false,
        "stroking_color": null,
        "non_stroking_color": [
            0
        ],
        "mcid": 79,
        "tag": "LBody",
        "object_type": "rect_edge",
        "page_number": 1,
        "stroking_pattern": null,
        "non_stroking_pattern": null,
        "top": 635.0096874999996,
        "bottom": 635.0096874999996,
        "doctop": 635.0096874999996,
        "orientation": "h"
    },
    {
        "x0": 33.26181818181818,
        "y0": 156.35999999999996,
        "x1": 33.26181818181818,
        "y1": 269.64000000000004,
        "width": 0,
        "height": 113.28000000000009,
        "pts": [
            [
                33.0,
                522.8399999999999
            ],
            [
                33.48,
                522.8399999999999
            ],
            [
                33.48,
                522.3599999999999
            ],
            [
                33.0,
                522.3599999999999
            ]
        ],
        "linewidth": 0,
        "stroke": false,
        "fill": true,
        "evenodd": false,
        "stroking_color": null,
        "non_stroking_color": [
            0
        ],
        "mcid": 71,
        "tag": "P",
        "object_type": "rect_edge",
        "page_number": 1,
        "stroking_pattern": null,
        "non_stroking_pattern": null,
        "top": 522.3599999999999,
        "bottom": 635.64,
        "doctop": 522.3599999999999,
        "orientation": "v"
    },
    {
        "x0": 39.0635294117647,
        "y0": 621.96,
        "x1": 39.0635294117647,
        "y1": 761.76,
        "width": 0,
        "height": 139.79999999999995,
        "pts": [
            [
                38.88,
                30.720000000000027
            ],
            [
                39.36,
                30.720000000000027
            ],
            [
                39.36,
                30.24000000000001
            ],
            [
                38.88,
                30.24000000000001
            ]
        ],
        "linewidth": 0,
        "stroke": false,
        "fill": true,
        "evenodd": false,
        "stroking_color": null,
        "non_stroking_color": [
            0
        ],
        "mcid": 3,
        "tag": "Artifact",
        "object_type": "rect_edge",
        "page_number": 1,
        "stroking_pattern": null,
        "non_stroking_pattern": null,
        "top": 30.24000000000001,
        "bottom": 170.03999999999996,
        "doctop": 30.24000000000001,
        "orientation": "v"
    },
    {
        "x0": 178.44000000000014,
        "y0": 660.6,
        "x1": 178.44000000000014,
        "y1": 746.881,
        "width": 0,
        "height": 86.28099999999995,
        "pts": [
            [
                39.36,
                45.60000000000002
            ],
            [
                178.2,
                45.60000000000002
            ],
            [
                178.2,
                45.11900000000003
            ],
            [
                39.36,
                45.11900000000003
            ]
        ],
        "linewidth": 0,
        "stroke": false,
        "fill": true,
        "evenodd": false,
        "stroking_color": null,
        "non_stroking_color": [
            0
        ],
        "mcid": 20,
        "tag": "Artifact",
        "object_type": "rect_edge",
        "page_number": 1,
        "stroking_pattern": null,
        "non_stroking_pattern": null,
        "top": 45.11900000000003,
        "bottom": 131.39999999999998,
        "doctop": 45.11900000000003,
        "orientation": "v"
    },
    {
        "x0": 305.77608247422853,
        "y0": 64.79999999999995,
        "x1": 305.77608247422853,
        "y1": 407.28000000000003,
        "width": 0,
        "height": 342.4800000000001,
        "pts": [
            [
                306.6,
                385.2
            ],
            [
                307.08000000000004,
                385.2
            ],
            [
                307.08000000000004,
                384.71999999999997
            ],
            [
                306.6,
                384.71999999999997
            ]
        ],
        "linewidth": 0,
        "stroke": false,
        "fill": true,
        "evenodd": false,
        "stroking_color": null,
        "non_stroking_color": [
            0
        ],
        "mcid": 93,
        "tag": "P",
        "object_type": "rect_edge",
        "page_number": 1,
        "stroking_pattern": null,
        "non_stroking_pattern": null,
        "top": 384.71999999999997,
        "bottom": 727.2,
        "doctop": 384.71999999999997,
        "orientation": "v"
    },
    {
        "x0": 571.4966470588226,
        "y0": 621.96,
        "x1": 571.4966470588226,
        "y1": 761.76,
        "width": 0,
        "height": 139.79999999999995,
        "pts": [
            [
                39.36,
                30.720000000000027
            ],
            [
                571.201,
                30.720000000000027
            ],
            [
                571.201,
                30.24000000000001
            ],
            [
                39.36,
                30.24000000000001
            ]
        ],
        "linewidth": 0,
        "stroke": false,
        "fill": true,
        "evenodd": false,
        "stroking_color": null,
        "non_stroking_color": [
            0
        ],
        "mcid": 3,
        "tag": "Artifact",
        "object_type": "rect_edge",
        "page_number": 1,
        "stroking_pattern": null,
        "non_stroking_pattern": null,
        "top": 30.24000000000001,
        "bottom": 170.03999999999996,
        "doctop": 30.24000000000001,
        "orientation": "v"
    },
    {
        "x0": 577.3124999999992,
        "y0": 64.79999999999995,
        "x1": 577.3124999999992,
        "y1": 407.28000000000003,
        "width": 0,
        "height": 342.4800000000001,
        "pts": [
            [
                307.08,
                385.2
            ],
            [
                577.0799999999999,
                385.2
            ],
            [
                577.0799999999999,
                384.71999999999997
            ],
            [
                307.08,
                384.71999999999997
            ]
        ],
        "linewidth": 0,
        "stroke": false,
        "fill": true,
        "evenodd": false,
        "stroking_color": null,
        "non_stroking_color": [
            0
        ],
        "mcid": 93,
        "tag": "P",
        "object_type": "rect_edge",
        "page_number": 1,
        "stroking_pattern": null,
        "non_stroking_pattern": null,
        "top": 384.71999999999997,
        "bottom": 727.2,
        "doctop": 384.71999999999997,
        "orientation": "v"
    }
]